kps9566/__init__.py
kps9566/kps9566.py
kps9566/kps9566_mapping.py
kps9566/replace_map.py
kps9566-0.7.0.dist-info/LICENSE
kps9566-0.7.0.dist-info/METADATA
kps9566-0.7.0.dist-info/WHEEL
kps9566-0.7.0.dist-info/top_level.txt
kps9566-0.7.0.dist-info/RECORD
