Metadata-Version: 2.1
Name: kps9566
Version: 0.7.0
Summary: KPS9566 codec for Python 3
Home-page: https://github.com/REO2248/kps9566py
Author: REO2248
Keywords: KPS9566,KPS 9566,국규9566,국규 9566,codec,korean
License-File: LICENSE
